techlens_cache_utils/__init__.py
techlens_cache_utils/main.py
techlens_cache_utils/sql/delete_record.sql
techlens_cache_utils/sql/get_record.sql
techlens_cache_utils/sql/get_record_hash_key.sql
techlens_cache_utils/sql/insert_record.sql
techlens_cache_utils/sql/make_table.sql
techlens_cache_utils/sql/update_record.sql
techlens_cache_utils-0.2.0.dist-info/METADATA
techlens_cache_utils-0.2.0.dist-info/WHEEL
techlens_cache_utils-0.2.0.dist-info/licenses/LICENSE
techlens_cache_utils-0.2.0.dist-info/RECORD
